pythas/__init__.py
pythas/compiler.py
pythas/core.py
pythas/types.py
pythas/utils.py
pythas/haskell/__init__.py
pythas/haskell/ghc.py
pythas/haskell/bin/Exports.hi
pythas/haskell/bin/Exports.o
pythas/haskell/bin/Foreign/Hasky.hi
pythas/haskell/bin/Foreign/Hasky.o
pythas/haskell/bin/Foreign/HaskyArray.hi
pythas/haskell/bin/Foreign/HaskyArray.o
pythas/haskell/bin/Foreign/HaskyList.hi
pythas/haskell/bin/Foreign/HaskyList.o
pythas/haskell/bin/Foreign/HaskyString.hi
pythas/haskell/bin/Foreign/HaskyString.o
pythas/haskell/bin/Foreign/HaskyTuple.hi
pythas/haskell/bin/Foreign/HaskyTuple.o
pythas/haskell/bin/Foreign/Pythas.hi
pythas/haskell/bin/Foreign/Pythas.o
pythas/haskell/bin/Foreign/C/Structs.hi
pythas/haskell/bin/Foreign/C/Structs.o
pythas/haskell/bin/Foreign/C/Structs/Templates.hi
pythas/haskell/bin/Foreign/C/Structs/Templates.o
pythas/haskell/bin/Foreign/C/Structs/Types.hi
pythas/haskell/bin/Foreign/C/Structs/Types.o
pythas/haskell/bin/Foreign/C/Structs/Utils.hi
pythas/haskell/bin/Foreign/C/Structs/Utils.o
pythas/haskell/bin/Foreign/Pythas/AST.hi
pythas/haskell/bin/Foreign/Pythas/AST.o
pythas/haskell/bin/Foreign/Pythas/Array.hi
pythas/haskell/bin/Foreign/Pythas/Array.o
pythas/haskell/bin/Foreign/Pythas/FFICreate.hi
pythas/haskell/bin/Foreign/Pythas/FFICreate.o
pythas/haskell/bin/Foreign/Pythas/FFIType.hi
pythas/haskell/bin/Foreign/Pythas/FFIType.o
pythas/haskell/bin/Foreign/Pythas/Finalizer.hi
pythas/haskell/bin/Foreign/Pythas/Finalizer.o
pythas/haskell/bin/Foreign/Pythas/HTypes.hi
pythas/haskell/bin/Foreign/Pythas/HTypes.o
pythas/haskell/bin/Foreign/Pythas/Hidden.hi
pythas/haskell/bin/Foreign/Pythas/Hidden.o
pythas/haskell/bin/Foreign/Pythas/List.hi
pythas/haskell/bin/Foreign/Pythas/List.o
pythas/haskell/bin/Foreign/Pythas/ParseExports.hi
pythas/haskell/bin/Foreign/Pythas/ParseExports.o
pythas/haskell/bin/Foreign/Pythas/ParseTypes.hi
pythas/haskell/bin/Foreign/Pythas/ParseTypes.o
pythas/haskell/bin/Foreign/Pythas/ParseUtils.hi
pythas-0.1b1.dist-info/COPYING
pythas-0.1b1.dist-info/COPYING.LESSER
pythas-0.1b1.dist-info/METADATA
pythas-0.1b1.dist-info/WHEEL
pythas-0.1b1.dist-info/top_level.txt
pythas-0.1b1.dist-info/RECORD
