Metadata-Version: 2.1
Name: pythas
Version: 0.1b1
Summary: Import Haskell modules as if they were Python modules
Home-page: https://github.com/pinselimo/Pythas
Author: Simon Plakolb
Author-email: s.plakolb@gmail.com
License: LGPLv3
Platform: any
Classifier: Development Status :: 4 - Beta
Classifier: License :: OSI Approved :: GNU Library or Lesser General Public License (LGPL)
Classifier: License :: OSI Approved :: GNU Lesser General Public License v3 (LGPLv3)
Classifier: License :: OSI Approved :: GNU Lesser General Public License v3 or later (LGPLv3+)
Classifier: Operating System :: OS Independent
Classifier: Intended Audience :: Developers
Classifier: Intended Audience :: Education
Classifier: Intended Audience :: Science/Research
Classifier: Programming Language :: Python
Classifier: Programming Language :: Python :: 3
Classifier: Programming Language :: Python :: 3.7
Classifier: Programming Language :: Python :: 3.8
Classifier: Programming Language :: Python :: 3.9
Classifier: Programming Language :: Haskell
Classifier: Topic :: Scientific/Engineering :: Physics
Classifier: Topic :: Scientific/Engineering :: Mathematics
Classifier: Topic :: Scientific/Engineering :: Information Analysis
Classifier: Topic :: Education
Classifier: Topic :: Software Development
Classifier: Typing :: Typed
Requires-Python: >=3.7
